Metadata-Version: 1.0
Name: GaussianBinomial-probabilty
Version: 0.1
Summary: Gaussian & Binomial distributions
Home-page: UNKNOWN
Author: Sandesh Jain
Author-email: jainsandesh414@gmail.com
License: UNKNOWN
Platform: UNKNOWN
